{
  "routes": [
    {
      "weight_name": "auto",
      "weight": 5390.372,
      "duration": 1248.12,
      "distance": 4689.244,
      "legs": [
        {
          "via_waypoints": [],
          "admins": [
            {
              "iso_3166_1_alpha3": "DEU",
              "iso_3166_1": "DE"
            }
          ],
          "weight": 628.844,
          "duration": 154.363,
          "steps": [],
          "distance": 788.216,
          "summary": "Oranienburger Straße, Monbijouplatz"
        },
        {
          "via_waypoints": [],
          "admins": [
            {
              "iso_3166_1_alpha3": "DEU",
              "iso_3166_1": "DE"
            }
          ],
          "weight": 1870.784,
          "duration": 313.461,
          "steps": [],
          "distance": 1151.395,
          "summary": "Anna-Louisa-Karsch-Straße, An der Spandauer Brücke"
        },
        {
          "via_waypoints": [],
          "admins": [
            {
              "iso_3166_1_alpha3": "DEU",
              "iso_3166_1": "DE"
            }
          ],
          "weight": 2571.426,
          "duration": 520.145,
          "steps": [],
          "distance": 1869.639,
          "summary": "Oranienburger Straße, Friedrichstraße"
        },
        {
          "via_waypoints": [],
          "admins": [
            {
              "iso_3166_1_alpha3": "DEU",
              "iso_3166_1": "DE"
            }
          ],
          "weight": 319.318,
          "duration": 260.151,
          "steps": [],
          "distance": 879.994,
          "summary": "Reichstagufer, Friedrichstraße"
        }
      ],
      "geometry": {
        "coordinates": [
          [
            13.388645,
            52.525936
          ],
          [
            13.388987,
            52.525933
          ],
          [
            13.389995,
            52.525692
          ],
          [
            13.397732,
            52.523753
          ],
          [
            13.398778,
            52.523335
          ],
          [
            13.398569,
            52.523004
          ],
          [
            13.400151,
            52.522687
          ],
          [
            13.40055,
            52.52196
          ],
          [
            13.400586,
            52.521554
          ],
          [
            13.400948,
            52.520801
          ],
          [
            13.404517,
            52.52196
          ],
          [
            13.403727,
            52.52306
          ],
          [
            13.402291,
            52.523681
          ],
          [
            13.401837,
            52.523651
          ],
          [
            13.399628,
            52.523675
          ],
          [
            13.399334,
            52.524371
          ],
          [
            13.398966,
            52.52431
          ],
          [
            13.399334,
            52.524371
          ],
          [
            13.399628,
            52.523675
          ],
          [
            13.397732,
            52.523753
          ],
          [
            13.392884,
            52.524984
          ],
          [
            13.392117,
            52.523557
          ],
          [
            13.387799,
            52.523401
          ],
          [
            13.387748,
            52.523877
          ],
          [
            13.387568,
            52.523863
          ],
          [
            13.388021,
            52.521765
          ],
          [
            13.385192,
            52.520099
          ],
          [
            13.38529,
            52.519653
          ],
          [
            13.387109,
            52.51977
          ],
          [
            13.387019,
            52.519848
          ],
          [
            13.386103,
            52.520063
          ],
          [
            13.385504,
            52.520288
          ],
          [
            13.388021,
            52.521765
          ],
          [
            13.3877,
            52.524433
          ],
          [
            13.387337,
            52.526239
          ],
          [
            13.388645,
            52.525936
          ]
        ],
        "type": "LineString"
      }
    }
  ],
  "waypoints": [
    {
      "distance": 29.999,
      "name": "Oranienburger Straße",
      "location": [
        13.388645,
        52.525936
      ]
    },
    {
      "distance": 69.202,
      "name": "Monbijouplatz",
      "location": [
        13.398569,
        52.523004
      ]
    },
    {
      "distance": 29.49,
      "name": "",
      "location": [
        13.398966,
        52.52431
      ]
    },
    {
      "distance": 21.304,
      "name": "Georgenstraße",
      "location": [
        13.386103,
        52.520063
      ]
    },
    {
      "distance": 29.999,
      "name": "Oranienburger Straße",
      "location": [
        13.388645,
        52.525936
      ]
    }
  ],
  "code": "Ok",
  "uuid": "98WPC9YLkWVICQC4e9jV7Bfcfe-96qk1NcP06oFh2onLobjkLbX-6Q=="
}